{
  "scriptCompleted": true,
  "filesAnalyzed": 5,
  "filesSkipped": [],
  "results": [
    {
      "path": "manuscript/references/Bendib 2024.md",
      "language": "markdown",
      "fileCategory": "docs",
      "totalLines": 2947,
      "nonEmptyLines": 1559,
      "sections": [
        {
          "heading": "**Final Year Project**",
          "level": 3,
          "line": 46
        },
        {
          "heading": "**Automatic Code Optimization in the MLIR Compiler Using Deep Reinforcement Learning**",
          "level": 1,
          "line": 52
        },
        {
          "heading": "**Dedication**",
          "level": 2,
          "line": 68
        },
        {
          "heading": "**Contents** {#contents}",
          "level": 1,
          "line": 78
        },
        {
          "heading": "**List of Algorithms** {#list-of-algorithms}",
          "level": 1,
          "line": 408
        },
        {
          "heading": "**Acronyms**",
          "level": 1,
          "line": 428
        },
        {
          "heading": "**Abstract** {#abstract}",
          "level": 1,
          "line": 478
        },
        {
          "heading": "**Résumé** {#résumé}",
          "level": 1,
          "line": 486
        },
        {
          "heading": "**General introduction** {#general-introduction}",
          "level": 1,
          "line": 495
        },
        {
          "heading": "**Chapter 1** {#chapter-1}",
          "level": 1,
          "line": 505
        },
        {
          "heading": "**Time Profiling**",
          "level": 4,
          "line": 541
        },
        {
          "heading": "**Memory Profiling**",
          "level": 4,
          "line": 547
        },
        {
          "heading": "**Chapter 2 Reinforcement learning** {#chapter-2-reinforcement-learning}",
          "level": 1,
          "line": 717
        },
        {
          "heading": "**Supervised learning**",
          "level": 4,
          "line": 727
        },
        {
          "heading": "**Unsupervised learning**",
          "level": 4,
          "line": 741
        },
        {
          "heading": "**Semi-Supervised learning**",
          "level": 4,
          "line": 753
        },
        {
          "heading": "**Self Supervised learning**",
          "level": 4,
          "line": 760
        },
        {
          "heading": "**Reinforcement learning**",
          "level": 4,
          "line": 766
        },
        {
          "heading": "**Feedforward Neural Networks (FNN)**",
          "level": 4,
          "line": 789
        },
        {
          "heading": "**Convolutional Neural Networks (CNN)**",
          "level": 4,
          "line": 793
        },
        {
          "heading": "**Recurrent Neural Networks ([Recurrent Neural Network (RNN)](#rnn-recurrent-neural-network-19))**",
          "level": 4,
          "line": 799
        },
        {
          "heading": "**Temporal Difference (TD)**",
          "level": 4,
          "line": 868
        },
        {
          "heading": "**Monte Carlo (MC)**",
          "level": 4,
          "line": 876
        },
        {
          "heading": "**Exploration vs Exploitation**",
          "level": 4,
          "line": 914
        },
        {
          "heading": "**Target Network**",
          "level": 4,
          "line": 924
        },
        {
          "heading": "**Experience Replay**",
          "level": 4,
          "line": 928
        },
        {
          "heading": "**DQN Algorithm**",
          "level": 4,
          "line": 932
        },
        {
          "heading": "**Double DQN**",
          "level": 4,
          "line": 964
        },
        {
          "heading": "**REINFORCE Algorithm**",
          "level": 4,
          "line": 976
        },
        {
          "heading": "**Surrogate Clipped Objective**",
          "level": 4,
          "line": 1013
        },
        {
          "heading": "**Chapter 3 Related Work** {#chapter-3-related-work}",
          "level": 1,
          "line": 1082
        },
        {
          "heading": "**Autotuning using Genetic Search (Ragan-Kelley et al., [2013](#pecenin,-m.,-maidl,-a.-m.,-&-weingaertner,-d.-\\(2019\\).-optimization-of-halide-image-pro--cessing-schedules-with-reinforcement-learning.-anais-do-xx-simpósio-em-sistemas-computacionais-de-alto-desempenho,-37–48.))**",
          "level": 4,
          "line": 1094
        },
        {
          "heading": "**Autotuning using Opentuner (Ansel et al., [2014](#ansel,-j.,-kamil,-s.,-veeramachaneni,-k.,-ragan-kelley,-j.,-bosboom,-j.,-o’reilly,-u.-m.,-&-amarasinghe,-s.-\\(2014\\).-opentuner:-an-extensible-framework-for-program-auto--tuning.-2014-23rd-international-conference-on-parallel-architecture-and-compi--lation-techniques-\\(pact\\),-303–315.-https://doi.org/10.1145/2628071.2628092))**",
          "level": 4,
          "line": 1100
        },
        {
          "heading": "**Automatical scheduling using partitioning (Mullapudi et al., [2016](#mnih,-v.,-kavukcuoglu,-k.,-silver,-d.,-rusu,-a.-a.,-veness,-j.,-bellemare,-m.-g.,-graves,-a.,-riedmiller,-m.,-fidjeland,-a.-k.,-ostrovski,-g.,-et-al.-\\(2015\\).-human-level-control-through-deep-reinforcement-learning.-nature,-518-\\(7540\\),-529–533.))**",
          "level": 4,
          "line": 1104
        },
        {
          "heading": "**Halide Schedule Optimization with Reinforcement Learning (Pecenin et al., [2019](#inc.-http-://-papers-.neurips.cc/-paper-/9015--pytorch--an---imperative---style---high---performance-deep-learning-library.pdf))**",
          "level": 4,
          "line": 1108
        },
        {
          "heading": "**Environment**",
          "level": 4,
          "line": 1151
        },
        {
          "heading": "**Agent**",
          "level": 4,
          "line": 1155
        },
        {
          "heading": "**Observation**",
          "level": 4,
          "line": 1159
        },
        {
          "heading": "**Action**",
          "level": 4,
          "line": 1168
        },
        {
          "heading": "**Reward**",
          "level": 4,
          "line": 1172
        },
        {
          "heading": "**Chapter 4 Design** {#chapter-4-design}",
          "level": 1,
          "line": 1348
        },
        {
          "heading": "**Policy Network with Unrolled Action Space**",
          "level": 4,
          "line": 1508
        },
        {
          "heading": "**Policy Network with Hierarchical Action Space**",
          "level": 4,
          "line": 1543
        },
        {
          "heading": "**Chapter 5 Implementation** {#chapter-5-implementation}",
          "level": 1,
          "line": 1738
        },
        {
          "heading": "**Torch**",
          "level": 4,
          "line": 1746
        },
        {
          "heading": "**Neptune**",
          "level": 4,
          "line": 1750
        },
        {
          "heading": "[**MLIR**](#mlir-multi-level-intermidiate-representation-13,-14,-47–49,-51,-58–64,-68,-70,-71,) **Python Bindings**",
          "level": 4,
          "line": 1760
        },
        {
          "heading": "6:   **if transformation is \"Tiling\" then**",
          "level": 4,
          "line": 1976
        },
        {
          "heading": "13:   **else if transformation is \"Tiling+Parallelization\" then**",
          "level": 4,
          "line": 1983
        },
        {
          "heading": "20:   **else if transformation is \"Interchange\" then**",
          "level": 4,
          "line": 1990
        },
        {
          "heading": "26:\t**else if transformation is \"Vectorization\" then**",
          "level": 4,
          "line": 1997
        },
        {
          "heading": "**Chapter 6** {#chapter-6}",
          "level": 1,
          "line": 2032
        },
        {
          "heading": "**Experimental Setup**",
          "level": 4,
          "line": 2080
        },
        {
          "heading": "**Hyperparameter\tValue**",
          "level": 4,
          "line": 2088
        },
        {
          "heading": "**Results**",
          "level": 4,
          "line": 2122
        },
        {
          "heading": "**Interpretation**",
          "level": 4,
          "line": 2189
        },
        {
          "heading": "**Conclusion**",
          "level": 4,
          "line": 2195
        },
        {
          "heading": "**Results**",
          "level": 4,
          "line": 2207
        },
        {
          "heading": "**Interpretation**",
          "level": 4,
          "line": 2257
        },
        {
          "heading": "**Conclusion**",
          "level": 4,
          "line": 2263
        },
        {
          "heading": "**Results**",
          "level": 4,
          "line": 2295
        },
        {
          "heading": "**Interpretation**",
          "level": 4,
          "line": 2299
        },
        {
          "heading": "**Conclusion**",
          "level": 4,
          "line": 2307
        },
        {
          "heading": "**Experimental Setup**",
          "level": 4,
          "line": 2317
        },
        {
          "heading": "**Results and Interpretation**",
          "level": 4,
          "line": 2321
        },
        {
          "heading": "**Conclusion**",
          "level": 4,
          "line": 2484
        },
        {
          "heading": "**General conclusion** {#general-conclusion}",
          "level": 1,
          "line": 2828
        },
        {
          "heading": "**Bibliography** {#bibliography}",
          "level": 1,
          "line": 2838
        }
      ],
      "metrics": {
        "importCount": 0,
        "exportCount": 0,
        "functionCount": 0,
        "classCount": 0,
        "sectionCount": 68
      }
    },
    {
      "path": "manuscript/references/Nassim & Mohamed 2025.md",
      "language": "markdown",
      "fileCategory": "docs",
      "totalLines": 2708,
      "nonEmptyLines": 1434,
      "sections": [
        {
          "heading": "**Final Year Thesis**",
          "level": 2,
          "line": 62
        },
        {
          "heading": "**Using Deep Reinforcement Learning for Automatic Code Optimization in the MLIR Compiler**",
          "level": 1,
          "line": 68
        },
        {
          "heading": "**Acknowledgments** {#acknowledgments}",
          "level": 1,
          "line": 82
        },
        {
          "heading": "**Abstract** {#abstract}",
          "level": 1,
          "line": 98
        },
        {
          "heading": "**Contents** {#contents}",
          "level": 1,
          "line": 106
        },
        {
          "heading": "**List of Figures** {#list-of-figures}",
          "level": 1,
          "line": 269
        },
        {
          "heading": "**Acronyms** {#acronyms}",
          "level": 1,
          "line": 367
        },
        {
          "heading": "**General Introduction** {#general-introduction}",
          "level": 1,
          "line": 424
        },
        {
          "heading": "**Chapter 1** {#chapter-1}",
          "level": 1,
          "line": 446
        },
        {
          "heading": "**Machine-Dependent Optimization**",
          "level": 4,
          "line": 474
        },
        {
          "heading": "**Machine-Independent Optimization**",
          "level": 4,
          "line": 488
        },
        {
          "heading": "**Hybrid Optimization**",
          "level": 4,
          "line": 509
        },
        {
          "heading": "**Chapter 2 Reinforcement Learning** {#chapter-2-reinforcement-learning}",
          "level": 1,
          "line": 708
        },
        {
          "heading": "**Vanilla Policy Gradient**",
          "level": 4,
          "line": 937
        },
        {
          "heading": "**Advantage Actor Critic (A2C)**",
          "level": 4,
          "line": 967
        },
        {
          "heading": "**Importance Sampling**",
          "level": 4,
          "line": 985
        },
        {
          "heading": "**Trust Region (TRPO)**",
          "level": 4,
          "line": 1002
        },
        {
          "heading": "**Proximal Policy Optimization (PPO)**",
          "level": 4,
          "line": 1014
        },
        {
          "heading": "**Self-Play**",
          "level": 4,
          "line": 1037
        },
        {
          "heading": "**Monte Carlo Tree Search (MCTS)**",
          "level": 4,
          "line": 1053
        },
        {
          "heading": "**Neural Network Training**",
          "level": 4,
          "line": 1098
        },
        {
          "heading": "**Chapter 3** {#chapter-3}",
          "level": 1,
          "line": 1156
        },
        {
          "heading": "**Optimizing Halide with Reinforcement Learning (Halide RL)**",
          "level": 4,
          "line": 1185
        },
        {
          "heading": "**Tiramisu’s Autoschedular**",
          "level": 4,
          "line": 1233
        },
        {
          "heading": "**Tiramisu RL**",
          "level": 4,
          "line": 1239
        },
        {
          "heading": "**System Architecture**",
          "level": 4,
          "line": 1268
        },
        {
          "heading": "**Key features**",
          "level": 4,
          "line": 1278
        },
        {
          "heading": "**Environments**",
          "level": 4,
          "line": 1288
        },
        {
          "heading": "**Challenges in Applying RL**",
          "level": 4,
          "line": 1325
        },
        {
          "heading": "**MDP-Based Formulation**",
          "level": 4,
          "line": 1335
        },
        {
          "heading": "**Rewards and Compilation**",
          "level": 4,
          "line": 1365
        },
        {
          "heading": "**General System Architecture**",
          "level": 4,
          "line": 1381
        },
        {
          "heading": "**Dataset Generation**",
          "level": 4,
          "line": 1397
        },
        {
          "heading": "**Agent**",
          "level": 4,
          "line": 1401
        },
        {
          "heading": "**States**",
          "level": 4,
          "line": 1405
        },
        {
          "heading": "**Actions**",
          "level": 4,
          "line": 1412
        },
        {
          "heading": "**Reward**",
          "level": 4,
          "line": 1418
        },
        {
          "heading": "**System Architecture**",
          "level": 4,
          "line": 1431
        },
        {
          "heading": "**States**",
          "level": 4,
          "line": 1441
        },
        {
          "heading": "**Actions**",
          "level": 4,
          "line": 1457
        },
        {
          "heading": "**Rewards**",
          "level": 4,
          "line": 1461
        },
        {
          "heading": "**Agent and Policy Network**",
          "level": 4,
          "line": 1475
        },
        {
          "heading": "**Polygym**",
          "level": 4,
          "line": 1555
        },
        {
          "heading": "**MLIR RL**",
          "level": 4,
          "line": 1589
        },
        {
          "heading": "**Chapter 4** {#chapter-4}",
          "level": 1,
          "line": 1672
        },
        {
          "heading": "**Updating Operation Features**",
          "level": 4,
          "line": 1814
        },
        {
          "heading": "**Tile Sizes**",
          "level": 4,
          "line": 1890
        },
        {
          "heading": "**Parallel Tile Sizes**",
          "level": 4,
          "line": 1894
        },
        {
          "heading": "**Interchange Permutation**",
          "level": 4,
          "line": 1900
        },
        {
          "heading": "**Input Layer**",
          "level": 4,
          "line": 1990
        },
        {
          "heading": "**Backbone**",
          "level": 4,
          "line": 1994
        },
        {
          "heading": "**Critic Head**",
          "level": 4,
          "line": 1998
        },
        {
          "heading": "**Actor Heads**",
          "level": 4,
          "line": 2002
        },
        {
          "heading": "**Proximal Policy Optimization**",
          "level": 4,
          "line": 2040
        },
        {
          "heading": "**AlphaZero**",
          "level": 4,
          "line": 2090
        },
        {
          "heading": "**Chapter 5** {#chapter-5}",
          "level": 1,
          "line": 2140
        },
        {
          "heading": "**MLIR Command Line**",
          "level": 4,
          "line": 2176
        },
        {
          "heading": "**MLIR Python Bindings**",
          "level": 4,
          "line": 2180
        },
        {
          "heading": "**Conclusion** {#conclusion-1}",
          "level": 1,
          "line": 2470
        },
        {
          "heading": "**Bibliography**",
          "level": 1,
          "line": 2480
        },
        {
          "heading": "**Appendix** {#appendix}",
          "level": 1,
          "line": 2583
        },
        {
          "heading": "**General Architecture**",
          "level": 2,
          "line": 2585
        },
        {
          "heading": "**LQCD IR**",
          "level": 2,
          "line": 2597
        },
        {
          "heading": "**Halide IR**",
          "level": 2,
          "line": 2607
        },
        {
          "heading": "**MLIR  Generation**",
          "level": 2,
          "line": 2688
        }
      ],
      "metrics": {
        "importCount": 0,
        "exportCount": 0,
        "functionCount": 0,
        "classCount": 0,
        "sectionCount": 65
      }
    },
    {
      "path": "manuscript/references/Rafik & Djad 2025.md",
      "language": "markdown",
      "fileCategory": "docs",
      "totalLines": 1957,
      "nonEmptyLines": 1086,
      "sections": [
        {
          "heading": "**University of Science and Technology Houari Boumediene**",
          "level": 4,
          "line": 4
        },
        {
          "heading": "**Supervised by:**",
          "level": 3,
          "line": 13
        },
        {
          "heading": "**Defense Date:**",
          "level": 3,
          "line": 21
        },
        {
          "heading": "**Acknowledgements**",
          "level": 1,
          "line": 27
        },
        {
          "heading": "**Abstract** {#abstract}",
          "level": 1,
          "line": 41
        },
        {
          "heading": "**R´esum´e** {#r´esum´e}",
          "level": 1,
          "line": 51
        },
        {
          "heading": "**Contents**",
          "level": 1,
          "line": 63
        },
        {
          "heading": "**List of Figures**",
          "level": 1,
          "line": 246
        },
        {
          "heading": "**List of Tables**",
          "level": 1,
          "line": 312
        },
        {
          "heading": "**General Introduction** {#general-introduction}",
          "level": 1,
          "line": 330
        },
        {
          "heading": "**Code Optimization**",
          "level": 1,
          "line": 342
        },
        {
          "heading": "**Benefits of Loop Parallelization:**",
          "level": 4,
          "line": 448
        },
        {
          "heading": "**Benefits of Loop Unrolling:**",
          "level": 4,
          "line": 462
        },
        {
          "heading": "**Benefits of Loop Skewing:**",
          "level": 4,
          "line": 477
        },
        {
          "heading": "**Benefits of Loop Tiling:**",
          "level": 4,
          "line": 493
        },
        {
          "heading": "**Benefits of Loop Inversion:**",
          "level": 4,
          "line": 507
        },
        {
          "heading": "**Benefits of Loop Unswitching:**",
          "level": 4,
          "line": 525
        },
        {
          "heading": "**Benefits of Loop Interchange**",
          "level": 4,
          "line": 540
        },
        {
          "heading": "**Benefits of Loop Vectorization**",
          "level": 4,
          "line": 552
        },
        {
          "heading": "**Benefits of Loop Fusion**",
          "level": 4,
          "line": 564
        },
        {
          "heading": "**Conclusion**",
          "level": 2,
          "line": 614
        },
        {
          "heading": "**Reinforcement Learning**",
          "level": 1,
          "line": 620
        },
        {
          "heading": "**Conclusion**",
          "level": 2,
          "line": 956
        },
        {
          "heading": "**Reinforcement Learning for Automatic Code Optimization**",
          "level": 1,
          "line": 962
        },
        {
          "heading": "**Environment**",
          "level": 4,
          "line": 973
        },
        {
          "heading": "**Observation**",
          "level": 4,
          "line": 977
        },
        {
          "heading": "**Actions**",
          "level": 4,
          "line": 984
        },
        {
          "heading": "**Agent**",
          "level": 4,
          "line": 989
        },
        {
          "heading": "**Reward types and formulas**",
          "level": 3,
          "line": 993
        },
        {
          "heading": "**State**",
          "level": 4,
          "line": 1034
        },
        {
          "heading": "**Actions**",
          "level": 4,
          "line": 1039
        },
        {
          "heading": "**Policy**",
          "level": 4,
          "line": 1059
        },
        {
          "heading": "**Rewards**",
          "level": 4,
          "line": 1066
        },
        {
          "heading": "**Frontend**",
          "level": 4,
          "line": 1082
        },
        {
          "heading": "**Backend**",
          "level": 4,
          "line": 1090
        },
        {
          "heading": "**LLVM Phase Ordering**",
          "level": 4,
          "line": 1096
        },
        {
          "heading": "**GCC Flag Selection**",
          "level": 4,
          "line": 1106
        },
        {
          "heading": "**CUDA Loop Nest Generation**",
          "level": 4,
          "line": 1122
        },
        {
          "heading": "**Autotuning Using Genetic Search**",
          "level": 3,
          "line": 1140
        },
        {
          "heading": "**Halide Schedule Optimization with Reinforcement Learning**",
          "level": 3,
          "line": 1146
        },
        {
          "heading": "**Analysis**",
          "level": 3,
          "line": 1273
        },
        {
          "heading": "**Conclusion**",
          "level": 2,
          "line": 1316
        },
        {
          "heading": "**Design & implementation**",
          "level": 1,
          "line": 1322
        },
        {
          "heading": "**else**",
          "level": 4,
          "line": 1460
        },
        {
          "heading": "**else**",
          "level": 4,
          "line": 1468
        },
        {
          "heading": "**else**",
          "level": 4,
          "line": 1499
        },
        {
          "heading": "**else**",
          "level": 4,
          "line": 1545
        },
        {
          "heading": "**else**",
          "level": 4,
          "line": 1552
        },
        {
          "heading": "**Pytorch**",
          "level": 4,
          "line": 1587
        },
        {
          "heading": "**Neptune**",
          "level": 4,
          "line": 1591
        },
        {
          "heading": "**MLIR**",
          "level": 4,
          "line": 1595
        },
        {
          "heading": "**Experiments and Results**",
          "level": 1,
          "line": 1658
        },
        {
          "heading": "**Analysis**",
          "level": 3,
          "line": 1754
        },
        {
          "heading": "**Results**",
          "level": 4,
          "line": 1779
        },
        {
          "heading": "**Conclusion**",
          "level": 4,
          "line": 1792
        },
        {
          "heading": "**Interpretation**",
          "level": 4,
          "line": 1838
        },
        {
          "heading": "**Conclusion**",
          "level": 4,
          "line": 1854
        },
        {
          "heading": "**General Conclusion** {#general-conclusion}",
          "level": 1,
          "line": 1858
        },
        {
          "heading": "**Bibliography**",
          "level": 1,
          "line": 1874
        }
      ],
      "metrics": {
        "importCount": 0,
        "exportCount": 0,
        "functionCount": 0,
        "classCount": 0,
        "sectionCount": 59
      }
    },
    {
      "path": "manuscript/references/manuscript_writing_comments.md",
      "language": "markdown",
      "fileCategory": "docs",
      "totalLines": 53,
      "nonEmptyLines": 42,
      "sections": [
        {
          "heading": "Manuscript Writing Comments",
          "level": 1,
          "line": 1
        },
        {
          "heading": "Text Formatting / Spelling / Grammar",
          "level": 2,
          "line": 3
        },
        {
          "heading": "Introduction",
          "level": 2,
          "line": 9
        },
        {
          "heading": "Bibliography",
          "level": 2,
          "line": 19
        },
        {
          "heading": "Structure",
          "level": 2,
          "line": 28
        },
        {
          "heading": "Writing Style",
          "level": 2,
          "line": 37
        },
        {
          "heading": "General",
          "level": 2,
          "line": 47
        }
      ],
      "metrics": {
        "importCount": 0,
        "exportCount": 0,
        "functionCount": 0,
        "classCount": 0,
        "sectionCount": 7
      }
    },
    {
      "path": "manuscript/references/mlir-rl-paper.md",
      "language": "markdown",
      "fileCategory": "docs",
      "totalLines": 778,
      "nonEmptyLines": 394,
      "sections": [
        {
          "heading": "A Reinforcement Learning Environment for Automatic Code Optimization in the MLIR Compiler",
          "level": 2,
          "line": 1
        },
        {
          "heading": "I. INTRODUCTION",
          "level": 2,
          "line": 21
        },
        {
          "heading": "II. BACKGROUND AND RELATED WORK",
          "level": 2,
          "line": 55
        },
        {
          "heading": "_A. MLIR_",
          "level": 2,
          "line": 59
        },
        {
          "heading": "_B. Machine Learning for Compilers_",
          "level": 2,
          "line": 65
        },
        {
          "heading": "_C. Reinforcement Learning for Compilers_",
          "level": 2,
          "line": 69
        },
        {
          "heading": "_D. MLIR-based Compilers for Machine Learning_",
          "level": 2,
          "line": 87
        },
        {
          "heading": "III. OVERVIEW OF MLIR RL",
          "level": 2,
          "line": 101
        },
        {
          "heading": "IV. REINFORCEMENT LEARNING ENVIRONMENT",
          "level": 2,
          "line": 119
        },
        {
          "heading": "_A. Action Space_",
          "level": 2,
          "line": 133
        },
        {
          "heading": "_B. States and Observations_",
          "level": 2,
          "line": 175
        },
        {
          "heading": "_C. Reward_",
          "level": 2,
          "line": 213
        },
        {
          "heading": "V. ACTOR-CRITIC NETWORK ARCHITECTURE",
          "level": 2,
          "line": 237
        },
        {
          "heading": "_A. Policy Network_",
          "level": 2,
          "line": 245
        },
        {
          "heading": "_B. Value Network_",
          "level": 2,
          "line": 267
        },
        {
          "heading": "VI. DATASET",
          "level": 2,
          "line": 271
        },
        {
          "heading": "_A. Deep Learning Data_",
          "level": 2,
          "line": 275
        },
        {
          "heading": "_B. LQCD Data_",
          "level": 2,
          "line": 298
        },
        {
          "heading": "VII. EXPERIMENTS AND RESULTS",
          "level": 2,
          "line": 308
        },
        {
          "heading": "_A. Experimental Setup_",
          "level": 2,
          "line": 310
        },
        {
          "heading": "_B. Overhead of the Compilation Pass_",
          "level": 2,
          "line": 344
        },
        {
          "heading": "_C. Evaluation Results_",
          "level": 2,
          "line": 348
        },
        {
          "heading": "_D. Ablation Study_",
          "level": 2,
          "line": 391
        },
        {
          "heading": "VIII. CHALLENGES AND FUTURE WORK",
          "level": 2,
          "line": 417
        },
        {
          "heading": "IX. CONCLUSION",
          "level": 2,
          "line": 421
        },
        {
          "heading": "X. DATA AVAILABILITY",
          "level": 2,
          "line": 425
        },
        {
          "heading": "XI. ACKNOWLEDGMENT",
          "level": 2,
          "line": 429
        },
        {
          "heading": "ARTIFACT APPENDIX",
          "level": 2,
          "line": 433
        },
        {
          "heading": "_A. Abstract_",
          "level": 2,
          "line": 435
        },
        {
          "heading": "_C. Description_",
          "level": 2,
          "line": 479
        },
        {
          "heading": "_D. Installation_",
          "level": 2,
          "line": 527
        },
        {
          "heading": "_E. Experiment workflow_",
          "level": 2,
          "line": 557
        },
        {
          "heading": "_G. Experiment customization_",
          "level": 2,
          "line": 591
        },
        {
          "heading": "_H. Notes_",
          "level": 2,
          "line": 605
        },
        {
          "heading": "REFERENCES",
          "level": 2,
          "line": 613
        },
        {
          "heading": "APPENDIX",
          "level": 2,
          "line": 725
        },
        {
          "heading": "_A. Action History Encoding_",
          "level": 2,
          "line": 727
        },
        {
          "heading": "_B. Level Pointers Detailed Explanation_",
          "level": 2,
          "line": 739
        },
        {
          "heading": "_D. Linalg Operation After Optimization_",
          "level": 2,
          "line": 773
        }
      ],
      "metrics": {
        "importCount": 0,
        "exportCount": 0,
        "functionCount": 0,
        "classCount": 0,
        "sectionCount": 39
      }
    }
  ]
}